{
  "$schema": "https://ui.shadcn.com/schema/registry-item.json",
  "name": "badge",
  "title": "Badge",
  "dependencies": [
    "@base-ui/react",
    "class-variance-authority"
  ],
  "registryDependencies": [
    "https://ui.hotfix.jobs/r/tokens.json",
    "https://ui.hotfix.jobs/r/utils.json"
  ],
  "files": [
    {
      "path": "registry/components/ui/badge.tsx",
      "content": "\"use client\";\n\nimport { mergeProps } from \"@base-ui/react/merge-props\";\nimport { useRender } from \"@base-ui/react/use-render\";\nimport { cva, type VariantProps } from \"class-variance-authority\";\nimport type * as React from \"react\";\nimport { cn } from \"@/lib/utils\";\n\nexport const badgeVariants = cva(\n  [\n    \"relative inline-flex shrink-0 items-center justify-center gap-1.5 whitespace-nowrap\",\n    \"font-medium\",\n    \"[&_svg]:pointer-events-none [&_svg]:shrink-0\",\n  ].join(\" \"),\n  {\n    defaultVariants: {\n      size: \"md\",\n      variant: \"default\",\n      shape: \"pill\",\n      contrast: \"high\",\n    },\n    variants: {\n      size: {\n        sm: \"px-2 py-[2px] text-label-12 [&_svg:not([class*='size-'])]:size-3\",\n        md: \"px-2.5 py-1 text-label-12 [&_svg:not([class*='size-'])]:size-3.5\",\n        lg: \"px-3 py-1.5 text-label-13 [&_svg:not([class*='size-'])]:size-4\",\n      },\n      variant: {\n        default: \"\",\n        success: \"\",\n        warning: \"\",\n        error: \"\",\n      },\n      shape: {\n        rounded: \"rounded-[var(--radius-6)]\",\n        pill: \"rounded-full\",\n      },\n      contrast: {\n        high: \"\",\n        low: \"\",\n      },\n    },\n    compoundVariants: [\n      // High contrast: solid saturated fill, light text.\n      // Status variants use the semantic role tokens (--error / --warning /\n      // --success), not the -700 accent step. The accent scale inverts in\n      // dark mode (green-700 becomes a light green), which would leave\n      // white-on-light-green with no contrast. The semantic roles are\n      // fixed hex values that read identically in both themes.\n      { variant: \"default\", contrast: \"high\", class: \"bg-gray-1000 text-background-100\" },\n      // Semantic solids pair with the matching -fg text token so the\n      // label color inverts with the theme (light: white text on dark\n      // fill; dark: dark text on bright fill), matching Vercel Geist.\n      { variant: \"success\", contrast: \"high\", class: \"bg-success text-success-fg\" },\n      { variant: \"warning\", contrast: \"high\", class: \"bg-warning text-warning-fg\" },\n      { variant: \"error\",   contrast: \"high\", class: \"bg-error text-error-fg\" },\n      // Low contrast: subtle tint, darker text. The 100/900 pair inverts\n      // in dark mode (100 becomes very dark, 900 becomes very light), so\n      // dark-on-light in light mode becomes light-on-dark in dark mode.\n      { variant: \"default\", contrast: \"low\", class: \"bg-gray-200 text-gray-1000\" },\n      { variant: \"success\", contrast: \"low\", class: \"bg-green-100 text-green-900\" },\n      { variant: \"warning\", contrast: \"low\", class: \"bg-amber-100 text-amber-900\" },\n      { variant: \"error\",   contrast: \"low\", class: \"bg-red-100 text-red-900\" },\n    ],\n  },\n);\n\nexport interface BadgeProps extends useRender.ComponentProps<\"span\"> {\n  variant?: VariantProps<typeof badgeVariants>[\"variant\"];\n  size?: VariantProps<typeof badgeVariants>[\"size\"];\n  shape?: VariantProps<typeof badgeVariants>[\"shape\"];\n  /** `high` = solid saturated fill (default). `low` = subtle tinted fill for dense surfaces. */\n  contrast?: VariantProps<typeof badgeVariants>[\"contrast\"];\n  /** Optional inline icon rendered before the label. */\n  icon?: React.ReactNode;\n}\n\nexport function Badge({\n  className,\n  variant,\n  size,\n  shape,\n  contrast,\n  icon,\n  render,\n  children,\n  ...props\n}: BadgeProps): React.ReactElement {\n  const defaultProps = {\n    className: cn(badgeVariants({ size, variant, shape, contrast }), className),\n    \"data-slot\": \"badge\",\n    children: (\n      <>\n        {icon}\n        {children}\n      </>\n    ),\n  };\n\n  return useRender({\n    defaultTagName: \"span\",\n    props: mergeProps<\"span\">(defaultProps, props),\n    render,\n  });\n}\n",
      "type": "registry:ui",
      "target": "components/ui/badge.tsx"
    }
  ],
  "type": "registry:ui"
}